world_map_generator/__init__.py
world_map_generator/default_values.py
world_map_generator/generation/__init__.py
world_map_generator/generation/biome_generator.py
world_map_generator/generation/chunk_generator.py
world_map_generator/generation/distortion_generator.py
world_map_generator/generation/fractal_generator.py
world_map_generator/generation/map_composer.py
world_map_generator/generation/map_modifier.py
world_map_generator/generation/round_structures_generator.py
world_map_generator/generation/primitives/__init__.py
world_map_generator/generation/primitives/round_structure.py
world_map_generator/map/__init__.py
world_map_generator/map/biome.py
world_map_generator/map/chunk.py
world_map_generator/map/map.py
world_map_generator/rendering/__init__.py
world_map_generator/rendering/map_renderer.py
world_map_generator/utils/__init__.py
world_map_generator/utils/bounding.py
world_map_generator/utils/utils.py
world_map_generator-0.3.0.dist-info/LICENSE
world_map_generator-0.3.0.dist-info/METADATA
world_map_generator-0.3.0.dist-info/WHEEL
world_map_generator-0.3.0.dist-info/top_level.txt
world_map_generator-0.3.0.dist-info/RECORD
