Metadata-Version: 2.1
Name: world_map_generator
Version: 0.3.0
Summary: Heightmap landscape generator which allows to generate and modify infinite size 2d worlds.
Home-page: https://github.com/Greewil/fractal-heightmap
Author: Greewil (Shishkin Sergey)
Author-email: shishkin.sergey.d@gmail.com
License: MIT
Keywords: python,map generation,world generation,heightmap
Classifier: License :: OSI Approved :: MIT License
Classifier: Intended Audience :: Developers
Classifier: Programming Language :: Python :: 3.10
Classifier: Operating System :: Unix
Classifier: Operating System :: MacOS :: MacOS X
Classifier: Operating System :: Microsoft :: Windows
Requires-Python: >=3.10
License-File: LICENSE
Requires-Dist: Pillow
Requires-Dist: numpy
Requires-Dist: scipy
Requires-Dist: typing-extensions
